docs/Makefile
docs/authors.rst
docs/conf.py
docs/contributing.rst
docs/fuzzyfinder.rst
docs/history.rst
docs/index.rst
docs/installation.rst
docs/make.bat
docs/usage.rst
fuzzyfinder/__init__.py
fuzzyfinder/main.py
fuzzyfinder-2.3.0.dist-info/licenses/AUTHORS.rst
fuzzyfinder-2.3.0.dist-info/licenses/LICENSE
tests/__init__.py
tests/test_fuzzyfinder.py
fuzzyfinder-2.3.0.dist-info/METADATA
fuzzyfinder-2.3.0.dist-info/WHEEL
fuzzyfinder-2.3.0.dist-info/top_level.txt
fuzzyfinder-2.3.0.dist-info/RECORD
