Metadata-Version: 2.4
Name: fuzzyfinder
Version: 2.3.0
Summary: Fuzzy Finder implemented in Python.
Author-email: Amjith Ramanujam <amjith.r@gmail.com>
License: BSD
Project-URL: homepage, https://github.com/amjith/fuzzyfinder
Requires-Python: >=3.10
License-File: LICENSE
License-File: AUTHORS.rst
Provides-Extra: dev
Requires-Dist: coverage>=7.2.7; extra == "dev"
Requires-Dist: pytest>=7.4.4; extra == "dev"
Requires-Dist: pytest-cov>=4.1.0; extra == "dev"
Requires-Dist: pdbpp>=0.10.3; extra == "dev"
Requires-Dist: ruff>=0.11.1; extra == "dev"
Requires-Dist: sphinx>=8.1.3; extra == "dev"
Requires-Dist: sphinx-rtd-theme>=3.0.2; extra == "dev"
Requires-Dist: mypy>=1.15.0; extra == "dev"
Dynamic: license-file
